{"data":[{"id":1847,"name":"Ph\u01b0\u1eddng Duy\u1ec7t Trung"},{"id":1846,"name":"Ph\u01b0\u1eddng \u0110\u1ec1 Th\u00e1m"},{"id":1848,"name":"Ph\u01b0\u1eddng Ho\u00e0 Chung"},{"id":1850,"name":"Ph\u01b0\u1eddng H\u1ee3p Giang"},{"id":1849,"name":"Ph\u01b0\u1eddng Ng\u1ecdc Xu\u00e2n"},{"id":1851,"name":"Ph\u01b0\u1eddng S\u00f4ng B\u1eb1ng"},{"id":1852,"name":"Ph\u01b0\u1eddng S\u00f4ng Hi\u1ebfn"},{"id":1853,"name":"Ph\u01b0\u1eddng T\u00e2n Giang"},{"id":11383,"name":"X\u00e3 Chu Trinh"},{"id":11384,"name":"X\u00e3 H\u01b0ng \u0110\u1ea1o"},{"id":11385,"name":"X\u00e3 V\u0129nh Quang"}]}