{"data":[{"id":4610,"name":"Th\u1ecb tr\u1ea5n Bo"},{"id":4612,"name":"X\u00e3 B\u1eafc S\u01a1n"},{"id":4613,"name":"X\u00e3 B\u00ecnh S\u01a1n"},{"id":4616,"name":"X\u00e3 Cu\u1ed1i H\u1ea1"},{"id":4617,"name":"X\u00e3 \u0110\u00f4ng B\u1eafc"},{"id":4618,"name":"X\u00e3 \u0110\u00fa S\u00e1ng"},{"id":4619,"name":"X\u00e3 H\u1ea1 B\u00ec"},{"id":4621,"name":"X\u00e3 H\u1ee3p \u0110\u1ed3ng"},{"id":4622,"name":"X\u00e3 H\u1ee3p Kim"},{"id":4624,"name":"X\u00e3 H\u00f9ng Ti\u1ebfn"},{"id":4625,"name":"X\u00e3 Kim B\u00ecnh"},{"id":4626,"name":"X\u00e3 Kim B\u00f4i"},{"id":4627,"name":"X\u00e3 Kim S\u01a1n"},{"id":4628,"name":"X\u00e3 Kim Ti\u1ebfn"},{"id":4629,"name":"X\u00e3 Kim Truy"},{"id":4630,"name":"X\u00e3 L\u1eadp Chi\u1ec7ng"},{"id":4632,"name":"X\u00e3 Mi H\u00f2a"},{"id":4633,"name":"X\u00e3 Nam Th\u01b0\u1ee3ng"},{"id":4634,"name":"X\u00e3 N\u1eadt S\u01a1n"},{"id":4635,"name":"X\u00e3 Nu\u00f4ng D\u0103m"},{"id":4636,"name":"X\u00e3 S\u00e0o B\u00e1y"},{"id":4637,"name":"X\u00e3 S\u01a1n Th\u1ee7y"},{"id":4641,"name":"X\u00e3 Th\u01b0\u1ee3ng B\u00ec"},{"id":4642,"name":"X\u00e3 Th\u01b0\u1ee3ng Ti\u1ebfn"},{"id":4643,"name":"X\u00e3 Trung B\u00ec"},{"id":4644,"name":"X\u00e3 T\u00fa S\u01a1n"},{"id":4645,"name":"X\u00e3 V\u0129nh \u0110\u1ed3ng"},{"id":4646,"name":"X\u00e3 V\u0129nh Ti\u1ebfn"}]}