{"data":[{"id":8236,"name":"Ph\u01b0\u1eddng B\u1ea1ch \u0110\u1eb1ng"},{"id":8237,"name":"Ph\u01b0\u1eddng B\u00e3i Ch\u00e1y"},{"id":8238,"name":"Ph\u01b0\u1eddng Cao Th\u1eafng"},{"id":8239,"name":"Ph\u01b0\u1eddng Cao Xanh"},{"id":8235,"name":"Ph\u01b0\u1eddng \u0110\u1ea1i Y\u00ean"},{"id":8240,"name":"Ph\u01b0\u1eddng Gi\u1ebfng \u0110\u00e1y"},{"id":8241,"name":"Ph\u01b0\u1eddng H\u00e0 Kh\u00e1nh"},{"id":8242,"name":"Ph\u01b0\u1eddng H\u00e0 Kh\u1ea9u"},{"id":8243,"name":"Ph\u01b0\u1eddng H\u00e0 L\u1ea7m"},{"id":8244,"name":"Ph\u01b0\u1eddng H\u00e0 Phong"},{"id":8245,"name":"Ph\u01b0\u1eddng H\u00e0 Trung"},{"id":8246,"name":"Ph\u01b0\u1eddng H\u00e0 Tu"},{"id":8247,"name":"Ph\u01b0\u1eddng H\u1ed3ng Gai"},{"id":8248,"name":"Ph\u01b0\u1eddng H\u1ed3ng H\u00e0"},{"id":8249,"name":"Ph\u01b0\u1eddng H\u1ed3ng H\u1ea3i"},{"id":8250,"name":"Ph\u01b0\u1eddng H\u00f9ng Th\u1eafng"},{"id":8251,"name":"Ph\u01b0\u1eddng Tr\u1ea7n H\u01b0ng \u0110\u1ea1o"},{"id":8252,"name":"Ph\u01b0\u1eddng Tu\u1ea7n Ch\u00e2u"},{"id":8254,"name":"Ph\u01b0\u1eddng Vi\u1ec7t H\u01b0ng"},{"id":8253,"name":"Ph\u01b0\u1eddng Y\u1ebft Ki\u00eau"}]}