{"data":[{"id":9095,"name":"Th\u1ecb tr\u1ea5n Ti\u1ec1n H\u1ea3i"},{"id":9096,"name":"X\u00e3 An Ninh"},{"id":9097,"name":"X\u00e3 B\u1eafc H\u1ea3i"},{"id":9098,"name":"X\u00e3 \u0110\u00f4ng C\u01a1"},{"id":9099,"name":"X\u00e3 \u0110\u00f4ng H\u1ea3i"},{"id":9100,"name":"X\u00e3 \u0110\u00f4ng Ho\u00e0ng"},{"id":9101,"name":"X\u00e3 \u0110\u00f4ng L\u00e2m"},{"id":9102,"name":"X\u00e3 \u0110\u00f4ng Long"},{"id":9103,"name":"X\u00e3 \u0110\u00f4ng Minh"},{"id":9104,"name":"X\u00e3 \u0110\u00f4ng Phong"},{"id":9105,"name":"X\u00e3 \u0110\u00f4ng Qu\u00ed"},{"id":9106,"name":"X\u00e3 \u0110\u00f4ng Tr\u00e0"},{"id":9107,"name":"X\u00e3 \u0110\u00f4ng Trung"},{"id":9108,"name":"X\u00e3 \u0110\u00f4ng Xuy\u00ean"},{"id":9109,"name":"X\u00e3 Nam Ch\u00ednh"},{"id":9110,"name":"X\u00e3 Nam C\u01b0\u1eddng"},{"id":9111,"name":"X\u00e3 Nam H\u00e0"},{"id":9112,"name":"X\u00e3 Nam H\u1ea3i"},{"id":9113,"name":"X\u00e3 Nam H\u1ed3ng"},{"id":9114,"name":"X\u00e3 Nam H\u01b0ng"},{"id":9115,"name":"X\u00e3 Nam Ph\u00fa"},{"id":9117,"name":"X\u00e3 Nam Thanh"},{"id":9116,"name":"X\u00e3 Nam Th\u1eafng"},{"id":9118,"name":"X\u00e3 Nam Th\u1ecbnh"},{"id":9119,"name":"X\u00e3 Nam Trung"},{"id":9120,"name":"X\u00e3 Ph\u01b0\u01a1ng C\u00f4ng"},{"id":9121,"name":"X\u00e3 T\u00e2y An"},{"id":9122,"name":"X\u00e3 T\u00e2y Giang"},{"id":9123,"name":"X\u00e3 T\u00e2y L\u01b0\u01a1ng"},{"id":9124,"name":"X\u00e3 T\u00e2y Ninh"},{"id":9125,"name":"X\u00e3 T\u00e2y Phong"},{"id":9126,"name":"X\u00e3 T\u00e2y S\u01a1n"},{"id":9127,"name":"X\u00e3 T\u00e2y Ti\u1ebfn"},{"id":9128,"name":"X\u00e3 V\u00e2n Tr\u01b0\u1eddng"},{"id":9129,"name":"X\u00e3 V\u0169 L\u0103ng"}]}