{"data":[{"id":910,"name":"Th\u1ecb tr\u1ea5n Th\u1ea1nh Ph\u00fa"},{"id":911,"name":"X\u00e3 An \u0110i\u1ec1n"},{"id":912,"name":"X\u00e3 An Nh\u01a1n"},{"id":913,"name":"X\u00e3 An Quy"},{"id":914,"name":"X\u00e3 An Th\u1ea1nh"},{"id":915,"name":"X\u00e3 An Thu\u1eadn"},{"id":916,"name":"X\u00e3 B\u00ecnh Th\u1ea1nh"},{"id":917,"name":"X\u00e3 \u0110\u1ea1i \u0110i\u1ec1n"},{"id":918,"name":"X\u00e3 Giao Th\u1ea1nh"},{"id":919,"name":"X\u00e3 H\u00f2a L\u1ee3i"},{"id":920,"name":"X\u00e3 M\u1ef9 An"},{"id":921,"name":"X\u00e3 M\u1ef9 H\u01b0ng"},{"id":922,"name":"X\u00e3 Ph\u00fa Kh\u00e1nh"},{"id":923,"name":"X\u00e3 Qu\u1edbi \u0110i\u1ec1n"},{"id":924,"name":"X\u00e3 T\u00e2n Phong"},{"id":925,"name":"X\u00e3 Th\u1ea1nh H\u1ea3i"},{"id":926,"name":"X\u00e3 Th\u1ea1nh Phong"},{"id":927,"name":"X\u00e3 Th\u1edbi Th\u1ea1nh"}]}